cjswidget/__init__.py
cjswidget/apps.py
cjswidget/widgets.py
cjswidget/static/cjswidget/choices.min.css
cjswidget/static/cjswidget/choices.min.js
cjswidget/templates/cjswidget/widget.html
django_cjswidget-0.4.1.dist-info/LICENSE
django_cjswidget-0.4.1.dist-info/WHEEL
django_cjswidget-0.4.1.dist-info/METADATA
django_cjswidget-0.4.1.dist-info/RECORD
