Metadata-Version: 2.1
Name: django-cjswidget
Version: 0.4.1
Summary: A replacement for the Select widget with fancy new features - powered by choices.js!
Home-page: https://github.com/dmptrluke/django-cjswidget
License: UNKNOWN
Author: Luke Rogers
Author-email: luke@dmptr.com
Requires-Python: >=3.6
Classifier: Programming Language :: Python :: 3
Classifier: Programming Language :: Python :: 3.6
Classifier: Programming Language :: Python :: 3.7
Classifier: Programming Language :: Python :: 3.8
Classifier: Development Status :: 4 - Beta
Classifier: Framework :: Django
Classifier: Intended Audience :: Developers
Classifier: License :: OSI Approved :: MIT License
Classifier: Operating System :: OS Independent
Requires-Dist: shortuuid
